treedoc/__init__.py
treedoc/__main__.py
treedoc/main.py
treedoc/printing.py
treedoc/traversal.py
treedoc/utils.py
treedoc/utils_deprecated.py
treedoc-1.0.0.dist-info/AUTHORS.md
treedoc-1.0.0.dist-info/LICENSE.md
treedoc-1.0.0.dist-info/METADATA
treedoc-1.0.0.dist-info/WHEEL
treedoc-1.0.0.dist-info/entry_points.txt
treedoc-1.0.0.dist-info/top_level.txt
treedoc-1.0.0.dist-info/RECORD
