Metadata-Version: 2.1
Name: treedoc
Version: 1.0.0
Summary: Minimalistic Python documentation for dendrophiles.
Home-page: https://github.com/tommyod/treedoc
Author: tommyod
Author-email: tod001@uib.no
Maintainer: tommyod, smu095, glemvik
Maintainer-email: treedoc.dev@gmail.com
License: MIT
Keywords: documentation, utility
Platform: UNKNOWN
Classifier: Programming Language :: Python :: 3
Classifier: Programming Language :: Python :: 3 :: Only
Classifier: Programming Language :: Python :: 3.6
Classifier: Programming Language :: Python :: 3.7
Classifier: Programming Language :: Python :: 3.8
Requires-Python: >=3.6
